splunktalib/__init__.py
splunktalib/common/__init__.py
splunktalib/common/consts.py
splunktalib/common/log.py
splunktalib/common/pattern.py
splunktalib/common/util.py
splunktalib/common/xml_dom_parser.py
splunktalib/concurrent/__init__.py
splunktalib/concurrent/concurrent_executor.py
splunktalib/concurrent/process_pool.py
splunktalib/concurrent/thread_pool.py
splunktalib/conf_manager/__init__.py
splunktalib/conf_manager/conf_endpoints.py
splunktalib/conf_manager/conf_manager.py
splunktalib/conf_manager/data_input_endpoints.py
splunktalib/conf_manager/property_endpoints.py
splunktalib/conf_manager/request.py
splunktalib/conf_manager/ta_conf_manager.py
splunktalib/credentials.py
splunktalib/event_writer.py
splunktalib/file_monitor.py
splunktalib/kv_client.py
splunktalib/modinput.py
splunktalib/orphan_process_monitor.py
splunktalib/rest.py
splunktalib/schedule/__init__.py
splunktalib/schedule/job.py
splunktalib/schedule/scheduler.py
splunktalib/setting.conf
splunktalib/splunk_cluster.py
splunktalib/splunk_platform.py
splunktalib/state_store.py
splunktalib/timer.py
splunktalib/timer_queue.py
splunktalib-3.0.2.dist-info/METADATA
splunktalib-3.0.2.dist-info/WHEEL
splunktalib-3.0.2.dist-info/LICENSE
splunktalib-3.0.2.dist-info/RECORD
